kat_cipher/__init__.py
kat_cipher/gui.py
kat_cipher/stegano.py
tests/__init__.py
tests/conftest.py
tests/test_imports.py
kat_cipher-1.0.1.dist-info/METADATA
kat_cipher-1.0.1.dist-info/WHEEL
kat_cipher-1.0.1.dist-info/entry_points.txt
kat_cipher-1.0.1.dist-info/top_level.txt
kat_cipher-1.0.1.dist-info/RECORD
