Metadata-Version: 2.4
Name: kat_cipher
Version: 1.0.1
Summary: A Python package for Sanskrit-based text steganography in images.
Home-page: https://github.com/YashAPro1/kat_cipher.git
Author: Yashkumar Dubey
Author-email: your.email@example.com
Classifier: Programming Language :: Python :: 3
Classifier: License :: OSI Approved :: MIT License
Classifier: Operating System :: OS Independent
Requires-Python: >=3.7
Requires-Dist: opencv-python>=4.9.0.80
Requires-Dist: numpy>=1.26.0
Requires-Dist: PyQt6>=6.4.2
Requires-Dist: PyQt6-tools==6.4.2.3.3
Requires-Dist: PyQt6-plugins==6.4.2.2.3
Dynamic: author
Dynamic: author-email
Dynamic: classifier
Dynamic: description
Dynamic: description-content-type
Dynamic: home-page
Dynamic: requires-dist
Dynamic: requires-python
Dynamic: summary
